wora/__init__.py
wora/cli.py
wora/config.py
wora/design.py
wora/dynmod.py
wora/file.py
wora/fn.py
wora/platforms.py
wora/syntax.py
wora/wora.py
wora-0.3.3.dist-info/LICENSE
wora-0.3.3.dist-info/METADATA
wora-0.3.3.dist-info/WHEEL
wora-0.3.3.dist-info/top_level.txt
wora-0.3.3.dist-info/RECORD
