Metadata-Version: 2.1
Name: wora
Version: 0.3.3
Summary: Write once, run anywhere, a python library with general purpose utilities.
Home-page: https://github.com/jmdaemon/wora
Author: Joseph Diza
Author-email: josephm.diza@gmail.com
License: GPLv3
Project-URL: Bug Tracker, https://github.com/jmdaemon/wora/issues
Classifier: Programming Language :: Python :: 3
Classifier: License :: OSI Approved :: GNU General Public License v3 or later (GPLv3+)
Classifier: Operating System :: OS Independent
Requires-Python: >=3.10
License-File: LICENSE
Requires-Dist: toml
